xtdate_utils/__init__.py
xtdate_utils/xtdate_utils.py
xt_TimeUtils-0.2.2.dist-info/LICENSE
xt_TimeUtils-0.2.2.dist-info/METADATA
xt_TimeUtils-0.2.2.dist-info/WHEEL
xt_TimeUtils-0.2.2.dist-info/top_level.txt
xt_TimeUtils-0.2.2.dist-info/RECORD
