Metadata-Version: 2.1
Name: xt-TimeUtils
Version: 0.2.2
Summary: A Tool For Processing Iteration Time
Home-page: https://github.com/mxtadmin/doap-date-utils
Author: Maoxinteng
Author-email: 1214403402@qq.com
License: UNKNOWN
Platform: UNKNOWN
Classifier: Programming Language :: Python :: 3.6
Classifier: License :: OSI Approved :: MIT License
Classifier: Operating System :: OS Independent
Requires-Python: >=3.6
Requires-Dist: arrow
